jk_regexhelper/FileNamePatternToRegExCompiler.py
jk_regexhelper/__init__.py
jk_regexhelper-0.2025.1.7.2.dist-info/WHEEL
jk_regexhelper-0.2025.1.7.2.dist-info/METADATA
jk_regexhelper-0.2025.1.7.2.dist-info/RECORD
